apis_highlighter/__init__.py
apis_highlighter/active_learning.py
apis_highlighter/admin.py
apis_highlighter/api_views.py
apis_highlighter/apps.py
apis_highlighter/forms.py
apis_highlighter/highlighter.py
apis_highlighter/migrations/0001_initial.py
apis_highlighter/migrations/0002_auto_20200121_1227.py
apis_highlighter/migrations/0003_annotationproject_published.py
apis_highlighter/migrations/0004_auto_20210623_2124.py
apis_highlighter/migrations/0005_remove_annotation_entity_link.py
apis_highlighter/migrations/0006_auto_20221012_1446.py
apis_highlighter/migrations/__init__.py
apis_highlighter/models.py
apis_highlighter/serializer.py
apis_highlighter/static/apis_highlighter/apis_highlighter.css
apis_highlighter/static/apis_highlighter/apis_highlighter.js
apis_highlighter/templates/apis_highlighter/calculate_agreement.html
apis_highlighter/tests.py
apis_highlighter/urls.py
apis_highlighter/views.py
apis_highlighter-1.0.3.dist-info/LICENSE
apis_highlighter-1.0.3.dist-info/METADATA
apis_highlighter-1.0.3.dist-info/WHEEL
apis_highlighter-1.0.3.dist-info/RECORD
