Metadata-Version: 2.1
Name: apis-highlighter
Version: 1.0.3
Summary: Highlighter module for annotations in APIS framework
License: MIT
Author: Matthias Schlögl
Author-email: m.schloegl@gmail.com
Requires-Python: >=3.7,<3.12
Classifier: License :: OSI Approved :: MIT License
Classifier: Programming Language :: Python :: 3
Classifier: Programming Language :: Python :: 3.7
Classifier: Programming Language :: Python :: 3.8
Classifier: Programming Language :: Python :: 3.9
Classifier: Programming Language :: Python :: 3.10
Classifier: Programming Language :: Python :: 3.11
